{"Bin He": {"ACM_author_81339503886": [], "ACM_author_81458647649": [], "ACM_author_81456618754": [], "ACM_author_99658650907": [], "ACM_author_81456618771": [], "ACM_author_81554294156": [], "ACM_author_99658650910": [], "ACM_author_81482649534": [], "ACM_author_81502778517": []}, "Florian Rosenberg": {"ACM_author_81300393701": [], "ACM_author_81548011873": []}, "Roland Siegwart": {"ACM_author_81325490184": []}, "Jitendra Malik": {"ACM_author_81100342430": [], "ACM_author_81501640501": []}, "Christopher Nevison": {"ACM_author_81100091319": []}, "Roy Williams": {"ACM_author_81408594258": [], "ACM_author_99658982109": []}, "Sparsh Mittal": {"ACM_author_81482652396": []}, "Audun Josang": {"ACM_author_81100343007": []}, "Mark Billinghurst": {"ACM_author_81100499261": [], "ACM_author_81548027994": []}, "Paul Havinga": {"ACM_author_81100053624": [], "ACM_author_81430601098": []}, "Bharat Bhargava": {"ACM_author_81100085687": [], "ACM_author_81440596660": [], "ACM_author_81481642164": [], "ACM_author_81556649856": []}, "Yaxin Bi": {"ACM_author_81309490325": [], "ACM_author_99659069040": [], "ACM_author_87058855357": []}, "Anthony J. Jakeman": {"ACM_author_81100383707": [], "ACM_author_81453634501": []}, "Thomas Eiter": {"ACM_author_81330490221": [], "ACM_author_81339498340": []}, "Mike Thelwall": {"ACM_author_81100370373": []}, "Mark Craven": {"ACM_author_81100554243": []}, "Jun Yan": {"ACM_author_99658653027": [], "ACM_author_81339538365": [], "ACM_author_81375615238": [], "ACM_author_81501658958": [], "ACM_author_81100045080": [], "ACM_author_81444604612": [], "ACM_author_81323497893": [], "ACM_author_99658697505": [], "ACM_author_81442604120": []}, "Ulrike Von Luxburg": {"ACM_author_81100383399": []}, "Vahid Tabataba Vakili": {"ACM_author_81381592661": [], "ACM_author_81414619486": []}, "Shengyong Chen": {"ACM_author_81407593156": []}, "Fabio Crestani": {"ACM_author_81100211564": [], "ACM_author_81548012361": []}, "Massimo de Santo": {"ACM_author_81100418923": []}, "A. Murat Tekalp": {"ACM_author_81100286212": [], "ACM_author_81442592756": []}, "Jean-Paul Bodeveix": {"ACM_author_81100590940": [], "ACM_author_81542768656": []}, "Rachid El Azouzi": {"ACM_author_81100247843": [], "ACM_author_81346487981": []}, "Pascal Fua": {"ACM_author_81548027691": [], "ACM_author_81100337078": [], "ACM_author_99659093839": []}, "Rahul Jain": {"ACM_author_81100114027": [], "ACM_author_81438594428": [], "ACM_author_81552849156": [], "ACM_author_81492651744": []}, "Gordon S Blair": {"ACM_author_81447603221": [], "ACM_author_81100419003": []}}